omega_prime/__init__.py
omega_prime/__main__.py
omega_prime/cli.py
omega_prime/locator.py
omega_prime/map.py
omega_prime/map_odr.py
omega_prime/maposicenterlinesegmentation.py
omega_prime/mapsegment.py
omega_prime/metrics.py
omega_prime/recording.py
omega_prime/schemas.py
omega_prime/types.py
omega_prime/converters/__init__.py
omega_prime/converters/converter.py
omega_prime/converters/lxd.py
omega_prime-0.2.0.dist-info/METADATA
omega_prime-0.2.0.dist-info/WHEEL
omega_prime-0.2.0.dist-info/entry_points.txt
omega_prime-0.2.0.dist-info/licenses/LICENSE
omega_prime-0.2.0.dist-info/RECORD
