Metadata-Version: 2.4
Name: omega-prime
Version: 0.2.0
Summary: Omega-Prime: Data Model, Data Format and Python Library for Handling Ground Truth Traffic Data
Project-URL: Homepage, https://github.com/ika-rwth-aachen/omega-prime
Project-URL: Repository, https://github.com/ika-rwth-aachen/omega-prime
Project-URL: Documentation, https://ika-rwth-aachen.github.io/omega-prime/
Author-email: Michael Schuldes <michael.schuldes@ika.rwth-aachen.de>, Sven Tarlowski <sven.tarlowski@ika.rwth-aachen.de>, ika - RWTH Aachen University <opensource@ika.rwth-aachen.de>
License: MPL-2.0
License-File: LICENSE
Keywords: automated-driving,omega-format,open-simulation-interface,osi,simulation,traffic
Classifier: License :: OSI Approved :: Mozilla Public License 2.0 (MPL 2.0)
Classifier: Operating System :: OS Independent
Classifier: Programming Language :: Python :: 3
Classifier: Programming Language :: Python :: 3.10
Classifier: Programming Language :: Python :: 3.11
Classifier: Programming Language :: Python :: 3.12
Classifier: Programming Language :: Python :: 3.13
Requires-Python: >=3.10
Requires-Dist: altair
Requires-Dist: betterosi<1,>=0.8.4
Requires-Dist: filelock>=3.18.0
Requires-Dist: joblib
Requires-Dist: lxd-io>=0.4.6
Requires-Dist: lxml
Requires-Dist: matplotlib
Requires-Dist: networkx
Requires-Dist: numpy
Requires-Dist: pandas[pyarrow]
Requires-Dist: pandera[polars]
Requires-Dist: polars
Requires-Dist: polars-st
Requires-Dist: pyproj
Requires-Dist: pyxodr-omega-prime
Requires-Dist: scipy
Requires-Dist: shapely
Requires-Dist: strenum
Requires-Dist: tqdm-joblib
Requires-Dist: typer
Requires-Dist: xarray
Provides-Extra: test
Requires-Dist: ipywidgets; extra == 'test'
Requires-Dist: mkdocs-jupyter; extra == 'test'
Requires-Dist: mkdocs-material; extra == 'test'
Requires-Dist: mkdocs-typer2; extra == 'test'
Requires-Dist: mkdocstrings[python]; extra == 'test'
Requires-Dist: nbval; extra == 'test'
Requires-Dist: pre-commit; extra == 'test'
Requires-Dist: pytest; extra == 'test'
Requires-Dist: pytest-codeblocks; extra == 'test'
Requires-Dist: pytest-cov; extra == 'test'
Requires-Dist: pytest-env; extra == 'test'
Requires-Dist: pytest-progress; extra == 'test'
Requires-Dist: pytest-sugar; extra == 'test'
Requires-Dist: ruff; extra == 'test'
